bddjango/MultipleConditionSearch.py
bddjango/PypiReadme.md
bddjango/Readme.md
bddjango/__init__.py
bddjango/autoCode.py
bddjango/autoWiki.py
bddjango/baseSearchView.py
bddjango/log.md
bddjango/pure.py
bddjango/adminclass/__init__.py
bddjango/adminclass/admin_env_init.py
bddjango/adminclass/adminclass.py
bddjango/django/__init__.py
bddjango/django/auth.py
bddjango/django/conf.py
bddjango/django/mixins.py
bddjango/django/models.py
bddjango/django/utils.py
bddjango/django/views.py
bddjango/logs/log2.md
bddjango/templates/autoCode.html
bddjango/templates/autoWiki.html
bddjango/templates/copyCode.html
bddjango/templates/admin/csv_form.html
bddjango/templates/admin/import_progress_bar.html
bddjango/templates/admin/simpleui_admin_actions.html
bddjango/templates/admin/guardian/model/simpleui_guardian_change_form.html
bddjango/templates/entities/base_change_list.html
bddjango/templates/entities/simpleui_change_list.html
bddjango/templates/entities/simpleui_change_list0.html
bddjango/templates/entities/simpleui_change_list_actions.html
bddjango/tools/__init__.py
bddjango/tools/base_orm_search.py
bddjango/tools/copy_to.py
bddjango/tools/create_user.py
bddjango/tools/csrf_exempt.py
bddjango/tools/db_utils.py
bddjango/tools/default
bddjango/tools/extractPdf.py
bddjango/tools/fake_model.py
bddjango/tools/generateModelCodeFromExcel.py
bddjango/tools/get_hot_keywords.py
bddjango/tools/get_user_ip.py
bddjango/tools/getshells.py
bddjango/tools/init_import_data_mixin.py
bddjango/tools/myflask.py
bddjango/tools/mylogger.py
bddjango/tools/nginx_config.py
bddjango/tools/remove_path.py
bddjango/tools/remove_temp_file.py
bddjango/tools/sort_dc_ls1_by_ls2.py
bddjango/tools/statistic_keywords_mixin.py
bddjango/tools/unzip_to.py
bddjango/tools/zipDir.py
bddjango/tools/extract_keyword/__init__.py
bddjango/tools/extract_keyword/extract_keyword.py
bddjango/tools/extract_keyword/stopwords.txt
bddjango/tools/extract_keyword/synonym_dict.txt
bddjango/tools/extract_keyword/user_dict.txt
bddjango-3.0.9.dist-info/METADATA
bddjango-3.0.9.dist-info/WHEEL
bddjango-3.0.9.dist-info/top_level.txt
bddjango-3.0.9.dist-info/RECORD
